README.rst
setup.py
Intellect.egg-info/PKG-INFO
Intellect.egg-info/SOURCES.txt
Intellect.egg-info/dependency_links.txt
Intellect.egg-info/requires.txt
Intellect.egg-info/top_level.txt
intellect/Callable.py
intellect/IO.py
intellect/Intellect.py
intellect/Node.py
intellect/PolicyLexer.py
intellect/PolicyTokenSource.py
intellect/__init__.py
intellect/reflection.py
intellect/examples/__init__.py
intellect/examples/bahBahBlackSheep/BagOfWool.py
intellect/examples/bahBahBlackSheep/BlackSheep.py
intellect/examples/bahBahBlackSheep/BuyOrder.py
intellect/examples/bahBahBlackSheep/Example.py
intellect/examples/bahBahBlackSheep/__init__.py
intellect/examples/bahBahBlackSheep/rulesets/__init__.py
intellect/examples/testing/ClassA.py
intellect/examples/testing/ClassCandD.py
intellect/examples/testing/ExerciseGrammar.py
intellect/examples/testing/ExerciseIntellect.py
intellect/examples/testing/Test.py
intellect/examples/testing/__init__.py
intellect/examples/testing/rulesets/__init__.py
intellect/examples/testing/subModule/ClassB.py
intellect/examples/testing/subModule/__init__.py
intellect/grammar/PolicyLexer.py
intellect/grammar/PolicyParser.py
intellect/grammar/__init__.py