Metadata-Version: 1.1
Name: Intellect
Version: 1.4.8.7
Summary: A Domain-specific language and Rules Engine for Python
Home-page: http://github.com/nemonik/Intellect
Author: Michael Joseph Walsh
Author-email: github.com{nospam}nemonik.com
License: BSD, 4-clause license
Keywords: intellect rules engine dsl policy
Platform: UNKNOWN
Classifier: Development Status :: 4 - Beta
Classifier: Intended Audience :: Developers
Classifier: License :: OSI Approved :: BSD License
Classifier: Operating System :: OS Independent
Classifier: Programming Language :: Python :: 2.6
Classifier: Programming Language :: Python :: 2.7
Classifier: Topic :: Software Development :: Libraries :: Python Modules
